{"nodes": [{"id": "c_users_samsung_downloads_sct_ontology_main_1_sct_ontology_main_scripts_seed_d1_ts", "label": "seed-d1.ts", "file_type": "code", "source_file": "C:\\Users\\SAMSUNG\\Downloads\\SCT_ONTOLOGY-main (1)\\SCT_ONTOLOGY-main\\scripts\\seed-d1.ts", "source_location": "L1"}], "edges": [{"source": "c_users_samsung_downloads_sct_ontology_main_1_sct_ontology_main_scripts_seed_d1_ts", "target": "node_child_process", "relation": "imports_from", "confidence": "EXTRACTED", "source_file": "C:\\Users\\SAMSUNG\\Downloads\\SCT_ONTOLOGY-main (1)\\SCT_ONTOLOGY-main\\scripts\\seed-d1.ts", "source_location": "L1", "weight": 1.0}, {"source": "c_users_samsung_downloads_sct_ontology_main_1_sct_ontology_main_scripts_seed_d1_ts", "target": "node_path", "relation": "imports_from", "confidence": "EXTRACTED", "source_file": "C:\\Users\\SAMSUNG\\Downloads\\SCT_ONTOLOGY-main (1)\\SCT_ONTOLOGY-main\\scripts\\seed-d1.ts", "source_location": "L2", "weight": 1.0}], "raw_calls": []}